{
  "lastUpdated": "2026-03-13T01:51:23.266681",
  "totalVideos": 50,
  "keywordTrends": [
    {
      "keyword": "3d motion design",
      "count": 10
    },
    {
      "keyword": "motion graphics 2024",
      "count": 10
    },
    {
      "keyword": "after effects animation",
      "count": 10
    },
    {
      "keyword": "blender motion graphics",
      "count": 10
    },
    {
      "keyword": "motion design trends",
      "count": 6
    },
    {
      "keyword": "cinema 4d motion",
      "count": 4
    }
  ],
  "platformStats": {
    "youtube": {
      "count": 50,
      "totalViews": 16193869
    },
    "vimeo": {
      "count": 0,
      "totalViews": 0
    }
  },
  "topVideos": [
    {
      "platform": "youtube",
      "id": "X6-rPcZd8q4",
      "title": "Octagon Monsters 💖💖💖",
      "description": "177. Adorable Octagon Monsters slowly awaken with the tiniest playful wiggles, each little eight-sided friend glowing softly as if ...",
      "thumbnail": "https://i.ytimg.com/vi/X6-rPcZd8q4/hqdefault.jpg",
      "channel": "Zeno3D",
      "publishedAt": "2026-03-04T21:00:00Z",
      "url": "https://www.youtube.com/watch?v=X6-rPcZd8q4",
      "viewCount": 5039556,
      "likeCount": 22417,
      "commentCount": 22,
      "duration": "PT20S",
      "keyword": "3d motion design",
      "collectedAt": "2026-03-13T01:50:31.970788",
      "engagementScore": 4.46
    },
    {
      "platform": "youtube",
      "id": "rDayPWwUhDQ",
      "title": "Funny Cube Monster 😂",
      "description": "Welcome to the Cute Shape Monster Universe! This channel features original 3D animated Shorts filled with adorable ...",
      "thumbnail": "https://i.ytimg.com/vi/rDayPWwUhDQ/hqdefault.jpg",
      "channel": "Gmaer 3D",
      "publishedAt": "2026-02-21T10:39:41Z",
      "url": "https://www.youtube.com/watch?v=rDayPWwUhDQ",
      "viewCount": 2298046,
      "likeCount": 10880,
      "commentCount": 5,
      "duration": "PT21S",
      "keyword": "3d motion design",
      "collectedAt": "2026-03-13T01:50:31.970795",
      "engagementScore": 4.74
    },
    {
      "platform": "youtube",
      "id": "l-_1pTW1yp4",
      "title": "BLACKPINK - 3rd MINI ALBUM [DEADLINE] ALBUM MOTION GRAPHIC",
      "description": "3rd MINI ALBUM [DEADLINE] 2026. 02. 27. 12AM(EST) / 2PM(KST) PRE-SAVE • ADD • ORDER ...",
      "thumbnail": "https://i.ytimg.com/vi/l-_1pTW1yp4/hqdefault.jpg",
      "channel": "BLACKPINK",
      "publishedAt": "2026-02-23T09:00:19Z",
      "url": "https://www.youtube.com/watch?v=l-_1pTW1yp4",
      "viewCount": 1536890,
      "likeCount": 194943,
      "commentCount": 8616,
      "duration": "PT40S",
      "keyword": "motion graphics 2024",
      "collectedAt": "2026-03-13T01:50:28.820793",
      "engagementScore": 138.05
    },
    {
      "platform": "youtube",
      "id": "RAPShoV06ds",
      "title": "Pac-Man VS Cube Monsters 😈⚔️😈",
      "description": "Pac-Man VS Cube Monsters ⚔️   #3danimationfilm #CuteBoxes #3DBoxes #cinema4d #C4DAnimation #CGI #visualart ...",
      "thumbnail": "https://i.ytimg.com/vi/RAPShoV06ds/hqdefault.jpg",
      "channel": "MDA 3D",
      "publishedAt": "2026-02-27T13:42:41Z",
      "url": "https://www.youtube.com/watch?v=RAPShoV06ds",
      "viewCount": 844663,
      "likeCount": 3323,
      "commentCount": 2,
      "duration": "PT16S",
      "keyword": "3d motion design",
      "collectedAt": "2026-03-13T01:50:31.970798",
      "engagementScore": 3.94
    },
    {
      "platform": "youtube",
      "id": "Gsy1Ar980fI",
      "title": "Cute Triangle Monsters 😈",
      "description": "Welcome to the Cute Shape Monster Universe! This channel features original 3D animated Shorts filled with adorable ...",
      "thumbnail": "https://i.ytimg.com/vi/Gsy1Ar980fI/hqdefault.jpg",
      "channel": "Gmaer 3D",
      "publishedAt": "2026-02-24T12:00:33Z",
      "url": "https://www.youtube.com/watch?v=Gsy1Ar980fI",
      "viewCount": 824270,
      "likeCount": 3758,
      "commentCount": 2,
      "duration": "PT21S",
      "keyword": "3d motion design",
      "collectedAt": "2026-03-13T01:50:31.970800",
      "engagementScore": 4.56
    },
    {
      "platform": "youtube",
      "id": "lKNhfLmM8Z0",
      "title": "Small Box Monsters 💖",
      "description": "10. Welcome to the Small Box Monsters collection — charming little creatures crafted from distinctive box-shaped designs.",
      "thumbnail": "https://i.ytimg.com/vi/lKNhfLmM8Z0/hqdefault.jpg",
      "channel": "Framer3D",
      "publishedAt": "2026-02-14T12:01:16Z",
      "url": "https://www.youtube.com/watch?v=lKNhfLmM8Z0",
      "viewCount": 537580,
      "likeCount": 1973,
      "commentCount": 4,
      "duration": "PT10S",
      "keyword": "3d motion design",
      "collectedAt": "2026-03-13T01:50:31.970805",
      "engagementScore": 3.69
    },
    {
      "platform": "youtube",
      "id": "-iynu-3qduA",
      "title": "Pac-Man VS Cube Monsters 😈⚔️😈",
      "description": "Pac-Man VS Cube Monsters ⚔️   #3danimationfilm #CuteBoxes #3DBoxes #cinema4d #C4DAnimation #CGI #visualart ...",
      "thumbnail": "https://i.ytimg.com/vi/-iynu-3qduA/hqdefault.jpg",
      "channel": "MDA 3D",
      "publishedAt": "2026-02-19T12:43:38Z",
      "url": "https://www.youtube.com/watch?v=-iynu-3qduA",
      "viewCount": 519465,
      "likeCount": 2008,
      "commentCount": 4,
      "duration": "PT19S",
      "keyword": "3d motion design",
      "collectedAt": "2026-03-13T01:50:31.970807",
      "engagementScore": 3.88
    },
    {
      "platform": "youtube",
      "id": "yyhevaXmkzo",
      "title": "Tiny Box Monster 💖",
      "description": "18. Welcome to Tiny Box Monster — an adorable little character shaped like a charming box. Drifting through a colorful, seamless ...",
      "thumbnail": "https://i.ytimg.com/vi/yyhevaXmkzo/hqdefault.jpg",
      "channel": "Framer3D",
      "publishedAt": "2026-02-23T15:01:40Z",
      "url": "https://www.youtube.com/watch?v=yyhevaXmkzo",
      "viewCount": 471955,
      "likeCount": 1976,
      "commentCount": 6,
      "duration": "PT22S",
      "keyword": "3d motion design",
      "collectedAt": "2026-03-13T01:50:31.970810",
      "engagementScore": 4.21
    },
    {
      "platform": "youtube",
      "id": "jZC7eqCtZj4",
      "title": "When Two Losers Become Goats - Naruto X Sasuke Edit | Montagem Alquimia",
      "description": "When Two Losers Become Goats - Naruto X Sasuke Edit | Montagem Alquimia #naruto #narutoedit #narutoshippuden #shorts ...",
      "thumbnail": "https://i.ytimg.com/vi/jZC7eqCtZj4/hqdefault.jpg",
      "channel": "Kito Kawi",
      "publishedAt": "2026-02-19T13:27:42Z",
      "url": "https://www.youtube.com/watch?v=jZC7eqCtZj4",
      "viewCount": 427157,
      "likeCount": 0,
      "commentCount": 447,
      "duration": "PT44S",
      "keyword": "after effects animation",
      "collectedAt": "2026-03-13T01:50:30.249176",
      "engagementScore": 2.09
    },
    {
      "platform": "youtube",
      "id": "JXeaXp8xnjc",
      "title": "Happy Box Monsters 💖💖💖",
      "description": "25. Welcome to the Happy Box Monsters collection — a delightful series of tiny creatures crafted from distinctive box-shaped ...",
      "thumbnail": "https://i.ytimg.com/vi/JXeaXp8xnjc/hqdefault.jpg",
      "channel": "Framer3D",
      "publishedAt": "2026-03-02T10:00:24Z",
      "url": "https://www.youtube.com/watch?v=JXeaXp8xnjc",
      "viewCount": 423051,
      "likeCount": 2105,
      "commentCount": 14,
      "duration": "PT21S",
      "keyword": "3d motion design",
      "collectedAt": "2026-03-13T01:50:31.970812",
      "engagementScore": 5.04
    },
    {
      "platform": "youtube",
      "id": "F4FulAOGljw",
      "title": "Adorable Circle Monsters in 3D ✨",
      "description": "Welcome to the Cute Shape Monster Universe! This channel features original 3D animated Shorts filled with adorable ...",
      "thumbnail": "https://i.ytimg.com/vi/F4FulAOGljw/hqdefault.jpg",
      "channel": "Gmaer 3D",
      "publishedAt": "2026-02-22T06:00:23Z",
      "url": "https://www.youtube.com/watch?v=F4FulAOGljw",
      "viewCount": 362103,
      "likeCount": 1688,
      "commentCount": 1,
      "duration": "PT26S",
      "keyword": "3d motion design",
      "collectedAt": "2026-03-13T01:50:31.970814",
      "engagementScore": 4.67
    },
    {
      "platform": "youtube",
      "id": "qhg2LJVEyuE",
      "title": "Happy Women’s Day Celebration | Women’s Day Wishes Status | March 8 Special",
      "description": "Happy Women's Day Celebration | Women's Day Wishes Status | March 8 Special Description: Celebrate the strength, love, and ...",
      "thumbnail": "https://i.ytimg.com/vi/qhg2LJVEyuE/hqdefault.jpg",
      "channel": "RT Nandhu's World",
      "publishedAt": "2026-03-07T11:30:48Z",
      "url": "https://www.youtube.com/watch?v=qhg2LJVEyuE",
      "viewCount": 269832,
      "likeCount": 1966,
      "commentCount": 22,
      "duration": "PT10S",
      "keyword": "motion graphics 2024",
      "collectedAt": "2026-03-13T01:50:28.820801",
      "engagementScore": 7.45
    },
    {
      "platform": "youtube",
      "id": "I4VtLbrwKRk",
      "title": "Gojo vs Yuji vs Dabura vs Sukuna | #edit #aftereffects #fyp #vs #debate #gojo #yuji #dabura #sukuna",
      "description": "",
      "thumbnail": "https://i.ytimg.com/vi/I4VtLbrwKRk/hqdefault.jpg",
      "channel": "レイ徒🇯🇵",
      "publishedAt": "2026-02-22T11:15:01Z",
      "url": "https://www.youtube.com/watch?v=I4VtLbrwKRk",
      "viewCount": 258642,
      "likeCount": 8602,
      "commentCount": 543,
      "duration": "PT35S",
      "keyword": "after effects animation",
      "collectedAt": "2026-03-13T01:50:30.249183",
      "engagementScore": 37.46
    },
    {
      "platform": "youtube",
      "id": "4dqlWkYCQwU",
      "title": "Happy Holi Pattern 2026 #holi #happyholi #rubikscube #3danimation #satisfying #knightcube",
      "description": "Step into a realm of creativity where Blender's remarkable animation and rendering capabilities meet ASMR-inducing sound ...",
      "thumbnail": "https://i.ytimg.com/vi/4dqlWkYCQwU/hqdefault.jpg",
      "channel": "Knightcube 3D",
      "publishedAt": "2026-03-04T05:30:00Z",
      "url": "https://www.youtube.com/watch?v=4dqlWkYCQwU",
      "viewCount": 257081,
      "likeCount": 572,
      "commentCount": 0,
      "duration": "PT4S",
      "keyword": "blender motion graphics",
      "collectedAt": "2026-03-13T01:50:31.353559",
      "engagementScore": 2.22
    },
    {
      "platform": "youtube",
      "id": "1UEMau403ms",
      "title": "clean the paint!!🖌️ #dandysworld #edit #animation #shorts #fyp  #viral #alightmotion #aftereffects",
      "description": "dandysworld #fyp #shorts #gachaclub #animation #edit #lazyedit.",
      "thumbnail": "https://i.ytimg.com/vi/1UEMau403ms/hqdefault.jpg",
      "channel": "Lytta_qwincc",
      "publishedAt": "2026-02-17T11:05:14Z",
      "url": "https://www.youtube.com/watch?v=1UEMau403ms",
      "viewCount": 247028,
      "likeCount": 0,
      "commentCount": 115,
      "duration": "PT24S",
      "keyword": "after effects animation",
      "collectedAt": "2026-03-13T01:50:30.249186",
      "engagementScore": 0.93
    },
    {
      "platform": "youtube",
      "id": "rL8tI-kP7Ao",
      "title": "Retopologizing into drawing Blender 2026",
      "description": "SUBSCRIBE FOR MORE Blender tips WHO IS BlenderHub? BlenderHub is for blender 3d artists, we create and share blender ...",
      "thumbnail": "https://i.ytimg.com/vi/rL8tI-kP7Ao/hqdefault.jpg",
      "channel": "BlenderHub ",
      "publishedAt": "2026-03-02T12:06:52Z",
      "url": "https://www.youtube.com/watch?v=rL8tI-kP7Ao",
      "viewCount": 227514,
      "likeCount": 2522,
      "commentCount": 38,
      "duration": "PT6S",
      "keyword": "blender motion graphics",
      "collectedAt": "2026-03-13T01:50:31.353549",
      "engagementScore": 11.42
    },
    {
      "platform": "youtube",
      "id": "CpoH9TGrwaE",
      "title": "Seedance 2.0 destroys Kling 3.0 and Veo 3 + Access",
      "description": "Seedance 2.0 is absolutely insane I wasn't really into versions 1.0 and 1.5 and didn't use them at all. But after running several ...",
      "thumbnail": "https://i.ytimg.com/vi/CpoH9TGrwaE/hqdefault.jpg",
      "channel": "re4ee",
      "publishedAt": "2026-02-14T12:28:42Z",
      "url": "https://www.youtube.com/watch?v=CpoH9TGrwaE",
      "viewCount": 220432,
      "likeCount": 4940,
      "commentCount": 353,
      "duration": "PT7M9S",
      "keyword": "3d motion design",
      "collectedAt": "2026-03-13T01:50:31.970803",
      "engagementScore": 25.61
    },
    {
      "platform": "youtube",
      "id": "pwuCMKwQRx4",
      "title": "3D Girl Made in 2D Style? by Blender artist Viserion93",
      "description": "SUBSCRIBE FOR MORE Blender tips WHO IS BlenderHub? BlenderHub is for blender 3d artists, we create and share blender ...",
      "thumbnail": "https://i.ytimg.com/vi/pwuCMKwQRx4/hqdefault.jpg",
      "channel": "BlenderHub ",
      "publishedAt": "2026-02-26T09:14:33Z",
      "url": "https://www.youtube.com/watch?v=pwuCMKwQRx4",
      "viewCount": 197031,
      "likeCount": 3212,
      "commentCount": 71,
      "duration": "PT4S",
      "keyword": "blender motion graphics",
      "collectedAt": "2026-03-13T01:50:31.353557",
      "engagementScore": 17.02
    },
    {
      "platform": "youtube",
      "id": "wgD1Duf7JNo",
      "title": "🔥 Perfect Fit 🔥 Wooden Physics Simulation in Blender 3D — Smooth Flow &amp; Satisfying Precision!",
      "description": "Smooth wooden flow with perfectly timed physics ✨ This Blender 3D Perfect Fit simulation highlights precise alignment, natural ...",
      "thumbnail": "https://i.ytimg.com/vi/wgD1Duf7JNo/hqdefault.jpg",
      "channel": "RenderZen",
      "publishedAt": "2026-03-09T11:46:06Z",
      "url": "https://www.youtube.com/watch?v=wgD1Duf7JNo",
      "viewCount": 174314,
      "likeCount": 0,
      "commentCount": 19,
      "duration": "PT14S",
      "keyword": "blender motion graphics",
      "collectedAt": "2026-03-13T01:50:31.353552",
      "engagementScore": 0.22
    },
    {
      "platform": "youtube",
      "id": "6OEa3i3CsKs",
      "title": "Instagram Viral Text Reels Tutorial | Instagram Trending Text Effect Reels Editing | Fisheye Text",
      "description": "Instagram Viral Text Reels Tutorial | Instagram Trending Text Effect Reels Editing | Fisheye Text Telegram Link ...",
      "thumbnail": "https://i.ytimg.com/vi/6OEa3i3CsKs/hqdefault.jpg",
      "channel": "Tech Lokesh",
      "publishedAt": "2026-03-08T06:10:07Z",
      "url": "https://www.youtube.com/watch?v=6OEa3i3CsKs",
      "viewCount": 157217,
      "likeCount": 2185,
      "commentCount": 35,
      "duration": "PT31S",
      "keyword": "after effects animation",
      "collectedAt": "2026-03-13T01:50:30.249191",
      "engagementScore": 14.34
    }
  ],
  "topEngagement": [
    {
      "platform": "youtube",
      "id": "l-_1pTW1yp4",
      "title": "BLACKPINK - 3rd MINI ALBUM [DEADLINE] ALBUM MOTION GRAPHIC",
      "description": "3rd MINI ALBUM [DEADLINE] 2026. 02. 27. 12AM(EST) / 2PM(KST) PRE-SAVE • ADD • ORDER ...",
      "thumbnail": "https://i.ytimg.com/vi/l-_1pTW1yp4/hqdefault.jpg",
      "channel": "BLACKPINK",
      "publishedAt": "2026-02-23T09:00:19Z",
      "url": "https://www.youtube.com/watch?v=l-_1pTW1yp4",
      "viewCount": 1536890,
      "likeCount": 194943,
      "commentCount": 8616,
      "duration": "PT40S",
      "keyword": "motion graphics 2024",
      "collectedAt": "2026-03-13T01:50:28.820793",
      "engagementScore": 138.05
    },
    {
      "platform": "youtube",
      "id": "kgwb-BpPSBA",
      "title": "How To Create Motion Graphics In Just 1 Minutes For FREE!",
      "description": "In this video I'll will Show you How You can create 3d motion Graphics without After effects Subscribe for more . . . For business ...",
      "thumbnail": "https://i.ytimg.com/vi/kgwb-BpPSBA/hqdefault.jpg",
      "channel": "Grow Teck",
      "publishedAt": "2026-02-15T03:14:41Z",
      "url": "https://www.youtube.com/watch?v=kgwb-BpPSBA",
      "viewCount": 78,
      "likeCount": 6,
      "commentCount": 2,
      "duration": "PT1M58S",
      "keyword": "motion graphics 2024",
      "collectedAt": "2026-03-13T01:50:28.820835",
      "engagementScore": 128.21
    },
    {
      "platform": "youtube",
      "id": "SSX5-u74RL0",
      "title": "Viral 3D Editing In CapCut PC 2026 🔥 Motion Graphics Edit Tutorial | CapCut PC Editing",
      "description": "Viral 3D Editing In CapCut PC 2026 | Motion Graphics Edit Tutorial Is video mein maine step-by-step bataya hai ki CapCut PC pe ...",
      "thumbnail": "https://i.ytimg.com/vi/SSX5-u74RL0/hqdefault.jpg",
      "channel": "Tech Saho",
      "publishedAt": "2026-03-10T14:30:31Z",
      "url": "https://www.youtube.com/watch?v=SSX5-u74RL0",
      "viewCount": 241,
      "likeCount": 14,
      "commentCount": 7,
      "duration": "PT15M35S",
      "keyword": "motion graphics 2024",
      "collectedAt": "2026-03-13T01:50:28.820828",
      "engagementScore": 116.18
    },
    {
      "platform": "youtube",
      "id": "y5Q-AhxPh9A",
      "title": "Apple Style UI Shape Morphing Tutorial in After Effects",
      "description": "Apple Style UI Shape Morphing Tutorial in After Effects Visit https://lumalabs.ai/naughtyyjuan to try The Dream Machine for free!",
      "thumbnail": "https://i.ytimg.com/vi/y5Q-AhxPh9A/hqdefault.jpg",
      "channel": "NaughtyyJuan",
      "publishedAt": "2026-02-25T21:01:35Z",
      "url": "https://www.youtube.com/watch?v=y5Q-AhxPh9A",
      "viewCount": 57223,
      "likeCount": 5638,
      "commentCount": 112,
      "duration": "PT16M41S",
      "keyword": "after effects animation",
      "collectedAt": "2026-03-13T01:50:30.249196",
      "engagementScore": 102.44
    },
    {
      "platform": "youtube",
      "id": "dr-tLGMySus",
      "title": "Stop Learning Blender Like Everyone Else",
      "description": "Use code smeaf at https://incogni.com/smeaf to get an exclusive 60% off. Stop learning Blender like everyone else. Donate to ...",
      "thumbnail": "https://i.ytimg.com/vi/dr-tLGMySus/hqdefault.jpg",
      "channel": "Smeaf",
      "publishedAt": "2026-02-11T06:38:33Z",
      "url": "https://www.youtube.com/watch?v=dr-tLGMySus",
      "viewCount": 29441,
      "likeCount": 2540,
      "commentCount": 154,
      "duration": "PT8M23S",
      "keyword": "blender motion graphics",
      "collectedAt": "2026-03-13T01:50:31.353566",
      "engagementScore": 96.74
    },
    {
      "platform": "youtube",
      "id": "5qQHTLiIhdQ",
      "title": "What is MOTION GRAPHICS and VFX in DaVinci Resolve",
      "description": "",
      "thumbnail": "https://i.ytimg.com/vi/5qQHTLiIhdQ/hqdefault.jpg",
      "channel": "CONTROL Z",
      "publishedAt": "2026-02-27T11:35:00Z",
      "url": "https://www.youtube.com/watch?v=5qQHTLiIhdQ",
      "viewCount": 8424,
      "likeCount": 713,
      "commentCount": 20,
      "duration": "PT1M13S",
      "keyword": "motion graphics 2024",
      "collectedAt": "2026-03-13T01:50:28.820805",
      "engagementScore": 89.39
    },
    {
      "platform": "youtube",
      "id": "_BFmg7xa0E8",
      "title": "3D Motion Graphics for AMAZON | C4D Style",
      "description": "This was made in After Effects only with no plugins Want to edit like me ? I am creating a course right now, sign up to get notified ...",
      "thumbnail": "https://i.ytimg.com/vi/_BFmg7xa0E8/hqdefault.jpg",
      "channel": "Kram.Visuals",
      "publishedAt": "2026-02-15T09:55:58Z",
      "url": "https://www.youtube.com/watch?v=_BFmg7xa0E8",
      "viewCount": 2802,
      "likeCount": 159,
      "commentCount": 32,
      "duration": "PT19S",
      "keyword": "cinema 4d motion",
      "collectedAt": "2026-03-13T01:50:30.816034",
      "engagementScore": 79.59
    },
    {
      "platform": "youtube",
      "id": "OXOxTgliegU",
      "title": "Which Is My Editing App? 💀😎 After Effect Edit |LUZ ROJA (SUPER SLOWED)",
      "description": "Which Is My Editing App? After Effect Edit |LUZ ROJA (SUPER SLOWED) #edit #viral #shorts Editing Software: Adobe After ...",
      "thumbnail": "https://i.ytimg.com/vi/OXOxTgliegU/hqdefault.jpg",
      "channel": "NOYON EDITS",
      "publishedAt": "2026-03-01T12:41:46Z",
      "url": "https://www.youtube.com/watch?v=OXOxTgliegU",
      "viewCount": 2586,
      "likeCount": 106,
      "commentCount": 41,
      "duration": "PT26S",
      "keyword": "motion graphics 2024",
      "collectedAt": "2026-03-13T01:50:28.820808",
      "engagementScore": 72.7
    },
    {
      "platform": "youtube",
      "id": "HUncjp9xA-M",
      "title": "Most Underrated Way To Use Blender!",
      "description": "I've been making these simple generative geometric motion graphics and been posting them on Instagram every day. and I think ...",
      "thumbnail": "https://i.ytimg.com/vi/HUncjp9xA-M/hqdefault.jpg",
      "channel": "Ducky 3D",
      "publishedAt": "2026-02-23T17:38:16Z",
      "url": "https://www.youtube.com/watch?v=HUncjp9xA-M",
      "viewCount": 28499,
      "likeCount": 1878,
      "commentCount": 93,
      "duration": "PT21M44S",
      "keyword": "blender motion graphics",
      "collectedAt": "2026-03-13T01:50:31.353569",
      "engagementScore": 72.42
    },
    {
      "platform": "youtube",
      "id": "4oNTuPmhgx0",
      "title": "Learn After Effects in 16 Minutes | Complete Tutorial",
      "description": "If After Effects has ever felt confusing or overwhelming, this video is for you. In just 16 minutes, we build an animated scene from ...",
      "thumbnail": "https://i.ytimg.com/vi/4oNTuPmhgx0/hqdefault.jpg",
      "channel": "Aasil Khan",
      "publishedAt": "2026-02-27T11:48:52Z",
      "url": "https://www.youtube.com/watch?v=4oNTuPmhgx0",
      "viewCount": 45222,
      "likeCount": 2762,
      "commentCount": 153,
      "duration": "PT16M39S",
      "keyword": "after effects animation",
      "collectedAt": "2026-03-13T01:50:30.249223",
      "engagementScore": 67.84
    }
  ],
  "summary": {
    "youtubeVideos": 50,
    "vimeoVideos": 0,
    "totalViews": 16193869,
    "avgEngagement": 36.43
  }
}